wp2github
