Metadata-Version: 1.0
Name: wp2github
Version: 1.1.3
Summary: Convert WordPress plugin readme file to GitHub Flavored Markdown
Home-page: https://github.com/r8/wp2github.py
Author: Sergey Storchay
Author-email: r8@r8.com.ua
License: Copyright (c) 2013, Sergey Storchay.
